{
  "platform": "x",
  "post_id": "1949574628181201282",
  "post_url": "https://x.com/i/status/1949574628181201282",
  "exported_at": "2026-07-12T18:31:41.605758+00:00",
  "comment_count": 17,
  "comments": [
    {
      "id": "1949579007151821221",
      "source": "x",
      "post_url": "https://x.com/i/status/1949574628181201282",
      "post_id": "1949574628181201282",
      "text": "@novarsonline Блокада је свима преко главе, јасно је да је реч о завери против државе и народе.",
      "author": "mkujovic_78",
      "created_at": "2025-07-27T21:13:51+00:00",
      "is_reply": true,
      "parent_comment_id": "1949574628181201282"
    },
    {
      "id": "1949756982400885156",
      "source": "x",
      "post_url": "https://x.com/i/status/1949574628181201282",
      "post_id": "1949574628181201282",
      "text": "@novarsonline 📌 https://t.co/Elgo76qbem",
      "author": "StarcebicG",
      "created_at": "2025-07-28T09:01:03+00:00",
      "is_reply": true,
      "parent_comment_id": "1949574628181201282"
    },
    {
      "id": "1949932939636043793",
      "source": "x",
      "post_url": "https://x.com/i/status/1949574628181201282",
      "post_id": "1949574628181201282",
      "text": "@novarsonline Ovdje nema niko ko nije član opozicionih partija.",
      "author": "ZRuzevic61852",
      "created_at": "2025-07-28T20:40:15+00:00",
      "is_reply": true,
      "parent_comment_id": "1949574628181201282"
    },
    {
      "id": "1949920963761692742",
      "source": "x",
      "post_url": "https://x.com/i/status/1949574628181201282",
      "post_id": "1949574628181201282",
      "text": "@novarsonline Kako nece kopati kad prekopase pola borskog okruga?Koje je to proseravanje jbt",
      "author": "BoraRamiz90998",
      "created_at": "2025-07-28T19:52:40+00:00",
      "is_reply": true,
      "parent_comment_id": "1949574628181201282"
    },
    {
      "id": "1949784385231659111",
      "source": "x",
      "post_url": "https://x.com/i/status/1949574628181201282",
      "post_id": "1949574628181201282",
      "text": "@novarsonline Znate onaj test , kao kojom brzinom pronađeš predmet na slici...e tako i ovde ko pronađe studenta na slici sledi nagrada 😀",
      "author": "vukanLobotic",
      "created_at": "2025-07-28T10:49:57+00:00",
      "is_reply": true,
      "parent_comment_id": "1949574628181201282"
    },
    {
      "id": "1949868336990314899",
      "source": "x",
      "post_url": "https://x.com/i/status/1949574628181201282",
      "post_id": "1949574628181201282",
      "text": "@novarsonline Полако људи свађом ништа не постижете.",
      "author": "MilicMilko99",
      "created_at": "2025-07-28T16:23:32+00:00",
      "is_reply": true,
      "parent_comment_id": "1949574628181201282"
    },
    {
      "id": "1949936208953376870",
      "source": "x",
      "post_url": "https://x.com/i/status/1949574628181201282",
      "post_id": "1949574628181201282",
      "text": "@novarsonline HAHAHAHA HAHAHAHA HAHAHAHAHA \nODAKLE U ARANJĐELIVCU LITIJUM?",
      "author": "MatejicZla12756",
      "created_at": "2025-07-28T20:53:14+00:00",
      "is_reply": true,
      "parent_comment_id": "1949574628181201282"
    },
    {
      "id": "1949577954113020102",
      "source": "x",
      "post_url": "https://x.com/i/status/1949574628181201282",
      "post_id": "1949574628181201282",
      "text": "@novarsonline Studiraš o životu iz fotelje, protestuješ protiv kopanja jer ti je ispod časti da neko uopšte radi.\nNećete kopati?\nU redu.\nAli nećete ni voditi Srbiju.",
      "author": "Lajava_Meta",
      "created_at": "2025-07-27T21:09:40+00:00",
      "is_reply": true,
      "parent_comment_id": "1949574628181201282"
    },
    {
      "id": "1949579594127769705",
      "source": "x",
      "post_url": "https://x.com/i/status/1949574628181201282",
      "post_id": "1949574628181201282",
      "text": "@novarsonline Koliko ispita su \" studenti \" položili ove godine?",
      "author": "kosaciantilopa",
      "created_at": "2025-07-27T21:16:11+00:00",
      "is_reply": true,
      "parent_comment_id": "1949574628181201282"
    },
    {
      "id": "1949774134851883207",
      "source": "x",
      "post_url": "https://x.com/i/status/1949574628181201282",
      "post_id": "1949574628181201282",
      "text": "@novarsonline Za to vreme.... https://t.co/YDKIxAY0uC",
      "author": "JrBotHunter",
      "created_at": "2025-07-28T10:09:13+00:00",
      "is_reply": true,
      "parent_comment_id": "1949574628181201282"
    },
    {
      "id": "1949576321085956470",
      "source": "x",
      "post_url": "https://x.com/i/status/1949574628181201282",
      "post_id": "1949574628181201282",
      "text": "@novarsonline A kada bi kojom kosmickom greskom blokaderi dosli navlast, kopalo bi se sve u 16!!!",
      "author": "HapsiAnarhiste",
      "created_at": "2025-07-27T21:03:10+00:00",
      "is_reply": true,
      "parent_comment_id": "1949574628181201282"
    },
    {
      "id": "1949828331504844972",
      "source": "x",
      "post_url": "https://x.com/i/status/1949574628181201282",
      "post_id": "1949574628181201282",
      "text": "@novarsonline Svi koji ruše svoju državu neće biti pitani ni  zašto, pa ni za litijum!!!\nOdlučit će većina i institucije izabrane od većine!",
      "author": "ljubo_sinergija",
      "created_at": "2025-07-28T13:44:34+00:00",
      "is_reply": true,
      "parent_comment_id": "1949574628181201282"
    },
    {
      "id": "1949791795673485591",
      "source": "x",
      "post_url": "https://x.com/i/status/1949574628181201282",
      "post_id": "1949574628181201282",
      "text": "@novarsonline A gde su vam ovde na slici studenti ovo su sve starci? Neverovatno je kako se političari u pokušaju i razni ološi kriju iza studenata . Uzaludni su ovi pokušaji udara na vlast sa svih frontova. Narod provalio.",
      "author": "MilovanVeliki",
      "created_at": "2025-07-28T11:19:24+00:00",
      "is_reply": true,
      "parent_comment_id": "1949574628181201282"
    },
    {
      "id": "1949816176739013058",
      "source": "x",
      "post_url": "https://x.com/i/status/1949574628181201282",
      "post_id": "1949574628181201282",
      "text": "@novarsonline Kopaće kopaće i te kako studenti,jel student i Koki🤣🤣🤣",
      "author": "DraganStokic4",
      "created_at": "2025-07-28T12:56:17+00:00",
      "is_reply": true,
      "parent_comment_id": "1949574628181201282"
    },
    {
      "id": "1950121257740988520",
      "source": "x",
      "post_url": "https://x.com/i/status/1949574628181201282",
      "post_id": "1949574628181201282",
      "text": "@novarsonline Kopace i te kako Rio Tinto. Vaš Boris Tadić i Djilas lopov su ih doveli,pa ste im prodali zemlju. Kopace se",
      "author": "Anti_Blokader",
      "created_at": "2025-07-29T09:08:34+00:00",
      "is_reply": true,
      "parent_comment_id": "1949574628181201282"
    },
    {
      "id": "1949590222951596268",
      "source": "x",
      "post_url": "https://x.com/i/status/1949574628181201282",
      "post_id": "1949574628181201282",
      "text": "@novarsonline Ovi jadni studenti vise ni sami ne znaju zasta pozivaju",
      "author": "PenezicKrcun",
      "created_at": "2025-07-27T21:58:25+00:00",
      "is_reply": true,
      "parent_comment_id": "1949574628181201282"
    },
    {
      "id": "1949782423237005639",
      "source": "x",
      "post_url": "https://x.com/i/status/1949574628181201282",
      "post_id": "1949574628181201282",
      "text": "@novarsonline Kopaćemo, a novu ss i ndh1 ćemo zakopati.",
      "author": "SrBinratnik",
      "created_at": "2025-07-28T10:42:09+00:00",
      "is_reply": true,
      "parent_comment_id": "1949574628181201282"
    }
  ]
}